{
  "timestamp": "2025-09-10T05:31:43.787Z",
  "summary": {
    "totalBrands": 75,
    "totalPhones": 5255
  },
  "brandDetails": [
    {
      "name": "xiaomi",
      "phones": 529,
      "lastUpdated": "2025-09-09 12:21:39",
      "file": "xiaomi.json"
    },
    {
      "name": "symphony",
      "phones": 498,
      "lastUpdated": "2025-09-09 12:24:08",
      "file": "symphony.json"
    },
    {
      "name": "samsung",
      "phones": 449,
      "lastUpdated": "2025-09-09 12:21:56",
      "file": "samsung.json"
    },
    {
      "name": "walton",
      "phones": 336,
      "lastUpdated": "2025-09-09 12:21:54",
      "file": "walton.json"
    },
    {
      "name": "realme",
      "phones": 285,
      "lastUpdated": "2025-09-09 12:21:46",
      "file": "realme.json"
    },
    {
      "name": "nokia",
      "phones": 283,
      "lastUpdated": "2025-09-09 12:21:45",
      "file": "nokia.json"
    },
    {
      "name": "vivo",
      "phones": 258,
      "lastUpdated": "2025-09-09 12:21:41",
      "file": "vivo.json"
    },
    {
      "name": "oppo",
      "phones": 224,
      "lastUpdated": "2025-09-09 12:21:31",
      "file": "oppo.json"
    },
    {
      "name": "maximus",
      "phones": 167,
      "lastUpdated": "2025-09-09 13:27:54",
      "file": "maximus.json"
    },
    {
      "name": "motorola",
      "phones": 151,
      "lastUpdated": "2025-09-09 12:24:29",
      "file": "motorola.json"
    },
    {
      "name": "huawei",
      "phones": 141,
      "lastUpdated": "2025-09-09 12:24:31",
      "file": "huawei.json"
    },
    {
      "name": "tecno",
      "phones": 141,
      "lastUpdated": "2025-09-09 12:21:47",
      "file": "tecno.json"
    },
    {
      "name": "oneplus",
      "phones": 116,
      "lastUpdated": "2025-09-09 12:21:46",
      "file": "oneplus.json"
    },
    {
      "name": "infinix",
      "phones": 114,
      "lastUpdated": "2025-09-09 12:21:47",
      "file": "infinix.json"
    },
    {
      "name": "itel",
      "phones": 105,
      "lastUpdated": "2025-09-09 12:21:50",
      "file": "itel.json"
    },
    {
      "name": "apple",
      "phones": 103,
      "lastUpdated": "2025-09-09 12:21:43",
      "file": "apple.json"
    },
    {
      "name": "honor",
      "phones": 99,
      "lastUpdated": "2025-09-09 19:08:54",
      "file": "honor.json"
    },
    {
      "name": "lava",
      "phones": 99,
      "lastUpdated": "2025-09-09 12:21:55",
      "file": "lava.json"
    },
    {
      "name": "iqoo",
      "phones": 86,
      "lastUpdated": "2025-09-09 12:24:29",
      "file": "iqoo.json"
    },
    {
      "name": "sony",
      "phones": 85,
      "lastUpdated": "2025-09-09 12:24:57",
      "file": "sony.json"
    },
    {
      "name": "micromax",
      "phones": 83,
      "lastUpdated": "2025-09-09 13:21:27",
      "file": "micromax.json"
    },
    {
      "name": "lg",
      "phones": 73,
      "lastUpdated": "2025-09-09 13:20:22",
      "file": "lg.json"
    },
    {
      "name": "zte",
      "phones": 71,
      "lastUpdated": "2025-09-09 13:18:52",
      "file": "zte.json"
    },
    {
      "name": "htc",
      "phones": 63,
      "lastUpdated": "2025-09-09 13:19:25",
      "file": "htc.json"
    },
    {
      "name": "okapia",
      "phones": 60,
      "lastUpdated": "2025-09-09 13:24:56",
      "file": "okapia.json"
    },
    {
      "name": "alcatel",
      "phones": 54,
      "lastUpdated": "2025-09-09 13:19:57",
      "file": "alcatel.json"
    },
    {
      "name": "google",
      "phones": 53,
      "lastUpdated": "2025-09-09 12:21:49",
      "file": "google.json"
    },
    {
      "name": "asus",
      "phones": 50,
      "lastUpdated": "2025-09-09 12:24:44",
      "file": "asus.json"
    },
    {
      "name": "mycell",
      "phones": 49,
      "lastUpdated": "2025-09-09 13:23:34",
      "file": "mycell.json"
    },
    {
      "name": "meizu",
      "phones": 40,
      "lastUpdated": "2025-09-09 13:16:32",
      "file": "meizu.json"
    },
    {
      "name": "kingstar",
      "phones": 35,
      "lastUpdated": "2025-09-09 13:22:35",
      "file": "kingstar.json"
    },
    {
      "name": "we",
      "phones": 35,
      "lastUpdated": "2025-09-09 13:18:27",
      "file": "we.json"
    },
    {
      "name": "doogee",
      "phones": 26,
      "lastUpdated": "2025-09-09 13:18:42",
      "file": "doogee.json"
    },
    {
      "name": "lenovo",
      "phones": 19,
      "lastUpdated": "2025-09-09 13:16:07",
      "file": "lenovo.json"
    },
    {
      "name": "tcl",
      "phones": 19,
      "lastUpdated": "2025-09-09 13:20:17",
      "file": "tcl.json"
    },
    {
      "name": "nothing",
      "phones": 18,
      "lastUpdated": "2025-09-09 12:23:18",
      "file": "nothing.json"
    },
    {
      "name": "5star",
      "phones": 17,
      "lastUpdated": "2025-09-09 13:17:51",
      "file": "5star.json"
    },
    {
      "name": "benco",
      "phones": 17,
      "lastUpdated": "2025-09-09 12:23:15",
      "file": "benco.json"
    },
    {
      "name": "proton",
      "phones": 17,
      "lastUpdated": "2025-09-09 13:19:34",
      "file": "proton.json"
    },
    {
      "name": "energizer",
      "phones": 15,
      "lastUpdated": "2025-09-09 13:20:56",
      "file": "energizer.json"
    },
    {
      "name": "helio",
      "phones": 14,
      "lastUpdated": "2025-09-09 12:23:04",
      "file": "helio.json"
    },
    {
      "name": "umidigi",
      "phones": 14,
      "lastUpdated": "2025-09-09 13:14:53",
      "file": "umidigi.json"
    },
    {
      "name": "coolpad",
      "phones": 13,
      "lastUpdated": "2025-09-09 13:15:11",
      "file": "coolpad.json"
    },
    {
      "name": "hmd",
      "phones": 11,
      "lastUpdated": "2025-09-09 13:16:38",
      "file": "hmd.json"
    },
    {
      "name": "oukitel",
      "phones": 11,
      "lastUpdated": "2025-09-09 13:19:48",
      "file": "oukitel.json"
    },
    {
      "name": "ulefone",
      "phones": 11,
      "lastUpdated": "2025-09-09 13:17:59",
      "file": "ulefone.json"
    },
    {
      "name": "gdl",
      "phones": 10,
      "lastUpdated": "2025-09-09 13:18:44",
      "file": "gdl.json"
    },
    {
      "name": "geo",
      "phones": 8,
      "lastUpdated": "2025-09-09 13:19:29",
      "file": "geo.json"
    },
    {
      "name": "microsoft",
      "phones": 8,
      "lastUpdated": "2025-09-09 13:14:58",
      "file": "microsoft.json"
    },
    {
      "name": "cubot",
      "phones": 7,
      "lastUpdated": "2025-09-09 13:15:35",
      "file": "cubot.json"
    },
    {
      "name": "gionee",
      "phones": 7,
      "lastUpdated": "2025-09-09 13:15:12",
      "file": "gionee.json"
    },
    {
      "name": "oscal",
      "phones": 7,
      "lastUpdated": "2025-09-09 13:19:44",
      "file": "oscal.json"
    },
    {
      "name": "bengal",
      "phones": 6,
      "lastUpdated": "2025-09-09 13:19:54",
      "file": "bengal.json"
    },
    {
      "name": "panasonic",
      "phones": 6,
      "lastUpdated": "2025-09-09 13:17:05",
      "file": "panasonic.json"
    },
    {
      "name": "blackview",
      "phones": 5,
      "lastUpdated": "2025-09-09 13:14:29",
      "file": "blackview.json"
    },
    {
      "name": "sharp",
      "phones": 5,
      "lastUpdated": "2025-09-09 13:19:07",
      "file": "sharp.json"
    },
    {
      "name": "philips",
      "phones": 4,
      "lastUpdated": "2025-09-09 13:20:08",
      "file": "philips.json"
    },
    {
      "name": "sonim",
      "phones": 4,
      "lastUpdated": "2025-09-09 13:18:48",
      "file": "sonim.json"
    },
    {
      "name": "allview",
      "phones": 3,
      "lastUpdated": "2025-09-09 13:16:31",
      "file": "allview.json"
    },
    {
      "name": "celkon",
      "phones": 3,
      "lastUpdated": "2025-09-09 13:17:03",
      "file": "celkon.json"
    },
    {
      "name": "hallo",
      "phones": 3,
      "lastUpdated": "2025-09-09 13:17:21",
      "file": "hallo.json"
    },
    {
      "name": "acer",
      "phones": 2,
      "lastUpdated": "2025-09-09 13:18:10",
      "file": "acer.json"
    },
    {
      "name": "blackberry",
      "phones": 1,
      "lastUpdated": "2025-09-09 13:16:14",
      "file": "blackberry.json"
    },
    {
      "name": "cat",
      "phones": 1,
      "lastUpdated": "2025-09-09 13:14:06",
      "file": "cat.json"
    },
    {
      "name": "freeyond",
      "phones": 1,
      "lastUpdated": "2025-09-09 13:15:41",
      "file": "freeyond.json"
    },
    {
      "name": "leica",
      "phones": 1,
      "lastUpdated": "2025-09-09 13:17:57",
      "file": "leica.json"
    },
    {
      "name": "leitz",
      "phones": 1,
      "lastUpdated": "2025-09-09 13:14:11",
      "file": "leitz.json"
    },
    {
      "name": "maxis",
      "phones": 1,
      "lastUpdated": "2025-09-09 13:16:45",
      "file": "maxis.json"
    },
    {
      "name": "nio",
      "phones": 1,
      "lastUpdated": "2025-09-09 13:14:15",
      "file": "nio.json"
    },
    {
      "name": "thuraya",
      "phones": 1,
      "lastUpdated": "2025-09-09 13:18:50",
      "file": "thuraya.json"
    },
    {
      "name": "wiko",
      "phones": 1,
      "lastUpdated": "2025-09-09 13:19:43",
      "file": "wiko.json"
    },
    {
      "name": "xtra",
      "phones": 1,
      "lastUpdated": "2025-09-09 13:17:08",
      "file": "xtra.json"
    },
    {
      "name": "blu",
      "phones": 0,
      "lastUpdated": "2025-09-09 13:14:02",
      "file": "blu.json"
    },
    {
      "name": "fairphone",
      "phones": 0,
      "lastUpdated": "2025-09-09 13:15:15",
      "file": "fairphone.json"
    },
    {
      "name": "kyocera",
      "phones": 0,
      "lastUpdated": "2025-09-09 13:14:03",
      "file": "kyocera.json"
    }
  ]
}